MANIFEST.in
README.md
setup.py
py_rinterpolate/__init__.py
py_rinterpolate/main.py
py_rinterpolate.egg-info/PKG-INFO
py_rinterpolate.egg-info/SOURCES.txt
py_rinterpolate.egg-info/dependency_links.txt
py_rinterpolate.egg-info/requires.txt
py_rinterpolate.egg-info/top_level.txt
src/py_rinterpolate_interface.c
src/librinterpolate/src/CHANGELOG
src/librinterpolate/src/Makefile
src/librinterpolate/src/pgo.sh
src/librinterpolate/src/rinterpolate-config.c
src/librinterpolate/src/rinterpolate.c
src/librinterpolate/src/rinterpolate.h
src/librinterpolate/src/rinterpolate_add_new_table.c
src/librinterpolate/src/rinterpolate_alloc_cacheline.c
src/librinterpolate/src/rinterpolate_alloc_dataspace.c
src/librinterpolate/src/rinterpolate_alloc_hypertable.c
src/librinterpolate/src/rinterpolate_alloc_varcount.c
src/librinterpolate/src/rinterpolate_build_flags.c
src/librinterpolate/src/rinterpolate_check_cache.c
src/librinterpolate/src/rinterpolate_compiler.h
src/librinterpolate/src/rinterpolate_construct_hypercube.c
src/librinterpolate/src/rinterpolate_error.c
src/librinterpolate/src/rinterpolate_free_data.c
src/librinterpolate/src/rinterpolate_free_hypertable.c
src/librinterpolate/src/rinterpolate_id_table.c
src/librinterpolate/src/rinterpolate_internal.h
src/librinterpolate/src/rinterpolate_interpolate.c
src/librinterpolate/src/rinterpolate_make_presearch.c
src/librinterpolate/src/rinterpolate_make_steps.c
src/librinterpolate/src/rinterpolate_other_searchers.h
src/librinterpolate/src/rinterpolate_prototypes.h
src/librinterpolate/src/rinterpolate_resize_cache.c
src/librinterpolate/src/rinterpolate_search_table.c
src/librinterpolate/src/rinterpolate_store_cache.c
src/librinterpolate/src/speeds
src/librinterpolate/src/speedtests.pl
src/librinterpolate/src/test_rinterpolate.c
src/librinterpolate/src/test_rinterpolate.sh