Metadata-Version: 2.1
Name: py-rinterpolate
Version: 0.13.0
Summary: Python wrapper for the linear interpolation library 'rinterpolate' (https://gitlab.eps.surrey.ac.uk/ri0005/librinterpolate)
Home-page: https://github.com/ddhendriks/py_rinterpolate
Author: David Hendriks, Robert Izzard
Author-email: davidhendriks93@gmail.com
Maintainer: David Hendriks
Maintainer-email: davidhendriks93@gmail.com
License: GPL
Keywords: linear interpolation,science
Platform: UNKNOWN
Classifier: Development Status :: 3 - Alpha
Classifier: License :: OSI Approved :: GNU General Public License v3 or later (GPLv3+)
Classifier: Intended Audience :: Developers
Classifier: Intended Audience :: Science/Research
Classifier: Operating System :: POSIX :: Linux
Classifier: Programming Language :: Python :: 3
Classifier: Programming Language :: C
Classifier: Topic :: Education
Classifier: Topic :: Scientific/Engineering :: Physics
Classifier: Topic :: Software Development :: Libraries :: Python Modules
Requires-Python: >=3.6
